db_validations/__init__.py
db_validations/_version.py
db_validations/db_validations.py
db_validations-0.1.1.dist-info/LICENSE
db_validations-0.1.1.dist-info/METADATA
db_validations-0.1.1.dist-info/WHEEL
db_validations-0.1.1.dist-info/top_level.txt
db_validations-0.1.1.dist-info/RECORD
