Metadata-Version: 2.1
Name: db-validations
Version: 0.1.1
Summary: UNKNOWN
Home-page: UNKNOWN
License: UNKNOWN
Platform: UNKNOWN
Requires-Python: >=3.7
Requires-Dist: pydantic
